upapasta/__init__.py
upapasta/main.py
upapasta/makepar.py
upapasta/makerar.py
upapasta/upfolder.py
upapasta-0.5.0.dist-info/licenses/LICENSE
upapasta-0.5.0.dist-info/METADATA
upapasta-0.5.0.dist-info/WHEEL
upapasta-0.5.0.dist-info/entry_points.txt
upapasta-0.5.0.dist-info/top_level.txt
upapasta-0.5.0.dist-info/RECORD
