Metadata-Version: 2.4
Name: upapasta
Version: 0.5.0
Summary: A script to upload folders to Usenet with RAR, PAR2, and nyuu.
Author-email: Franzopl <franzopl@example.com>
Project-URL: Homepage, https://github.com/franzopl/upapasta
Project-URL: Repository, https://github.com/franzopl/upapasta.git
Project-URL: Issues, https://github.com/franzopl/upapasta/issues
Classifier: Programming Language :: Python :: 3
Classifier: License :: OSI Approved :: MIT License
Classifier: Operating System :: OS Independent
Classifier: Topic :: Communications :: File Sharing
Classifier: Development Status :: 4 - Beta
Classifier: Intended Audience :: End Users/Desktop
Requires-Python: >=3.8
License-File: LICENSE
Dynamic: license-file
